Workbook

Sheet Read Me & Verdict
B2: Model 1 vs Model 2 — where the value lies
B3: Adviser time-saving SaaS versus a consumer AI-education funnel monetised by consented adviser referrals (+ minor ads). Assessed for venture-scale ambition. Blue = editable input.
B5: Verdict
B6: For venture scale, Model 2 is the stronger shape.
B7: • | C7: Why: it has venture precedent (SmartAsset reached unicorn status on this exact model; NerdWallet IPO'd; Credit Karma sold to Intuit for $7.1bn), it is geography-portable, it builds a data + brand + network moat rather than renting one, it uses your education strength, and it is lighter-touch on regulation (guidance, not automated advice).
B8: • | C8: Correction 1 — it is a LEADS business, not an ADS business. A consented, pre-qualified advice lead is worth €40–150 (UK) or $25–680 (US, by assets). Ads only pay at NerdWallet-scale traffic. In every scenario on the next sheet, referral fees dwarf ad revenue ~5:1 or more. Don't position it as ad-funded.
B9: • | C9: Correction 2 — build it as a CONSENTED WARM INTRODUCTION, not 'selling data'. That distinction is the difference between a fundable marketplace (SmartAsset/Unbiased) and a GDPR/reputation liability. The consumer chooses to be connected; that consent is the product.
B10: • | C10: Model 1 is not dead — it becomes the downstream upsell: once you own the consumer funnel and the advisers paying for your leads, you sell those same advisers tools. That stack (consumer acquisition → lead marketplace → adviser SaaS) is a far stronger venture narrative than either piece alone.
B11: • | C11: The real risk in Model 2 is consumer acquisition cost / marketplace cold-start. Your unfair advantage on precisely that risk is organic education content + the auto-enrolment SEO wave + a QFA's trust. That is the one place your edge attacks the hardest problem.
B13: The honest catch
B14: Model 2 has the higher ceiling AND the higher execution risk. Model 1 is lower-risk recurring SaaS but lower-ceiling and you're poorly positioned against funded incumbents. Given you're swinging for scale, the risk is the price of admission — but the plan must attack CAC deliberately, or it stalls like most consumer fintech.

Sheet Model 2 — Lead-Gen
B2: Model 2 — consumer AI education → consented referrals
B3: Funnel: visitors → complete an AI planning chat → a share consent to a warm adviser intro (sold as a qualified lead). Ads/affiliate are secondary. Blue = input, yellow = key lever.
B5: Shared assumptions
B6: Visitor → completed AI chat (engagement) | C6: 0.15 | E6: Generous; most content converts far lower
B7: Completed chat → consents to adviser intro | C7: 0.2 | E7: Of engaged users, share opting to be connected
B8: Revenue per consented qualified lead (€) | C8: 80 | E8: UK avg ~£65; US $25–680 by assets. Exclusive+pre-qualified = premium
B9: Ad + affiliate revenue per visitor / yr (€) | C9: 0.5 | E9: Blended RPM; finance CPMs are high but need volume
B11: Scenarios
B12: Annual unique visitors → | C12: Beachhead (IE) | D12: Scaled (UK/EU) | E12: Ambitious
B13: Unique visitors / year | C13: 100000 | D13: 1000000 | E13: 4000000
B14: Completed AI chats | C14: =C13*C6 -> 15000 | D14: =D13*C6 -> 150000 | E14: =E13*C6 -> 600000
B15: Consented qualified leads | C15: =C13*C6*C7 -> 3000 | D15: =D13*C6*C7 -> 30000 | E15: =E13*C6*C7 -> 120000
B16: Lead / referral revenue | C16: =C13*C6*C7*C8 -> 240000 | D16: =D13*C6*C7*C8 -> 2400000 | E16: =E13*C6*C7*C8 -> 9600000
B17: Ad + affiliate revenue | C17: =C13*C9 -> 50000 | D17: =D13*C9 -> 500000 | E17: =E13*C9 -> 2000000
B18: Total revenue | C18: =C16+C17 -> 290000 | D18: =D16+D17 -> 2900000 | E18: =E16+E17 -> 11600000
B19: Share from referrals (not ads) | C19: =C16/C18 -> 0.82758621 | D19: =D16/D18 -> 0.82758621 | E19: =E16/E18 -> 0.82758621 | F19: ← leads dominate; ads are a minor layer
B20: Reading: even with a generous ad RPM, referral fees are ~5x ad revenue or more. The consented lead is the product; the AI chat exists to qualify it.

Sheet Model 1 — Adviser SaaS
B2: Model 1 — save adviser time, at venture scale
B3: Recurring SaaS: cleaner revenue, but the ceiling is seats × price, and you're late against funded incumbents (Aveni, AdvisoryAI). This shows the penetration each ARR target demands.
B5: Inputs
B6: Price per adviser seat / year (€) | C6: 1200 | E6: Repriced from €2,400 to give buyers real ROI
B7: UK retail adviser posts (denominator) | C7: 37441 | E7: FCA 2024 retail intermediary data
B8: Ireland adviser seats (narrow) | C8: 1061 | E8: FPSB holistic planners
B10: Seats & market penetration required for each ARR target
B11: Target ARR | C11: Seats needed | D11: % of UK adviser base | E11: Reality check
B12: 500000 | C12: =B12/C6 -> 416.66667 | D12: =(B12/C6)/C7 -> 0.01112862 | E12: Feasible niche
B13: 2000000 | C13: =B13/C6 -> 1666.6667 | D13: =(B13/C6)/C7 -> 0.044514481 | E13: Hard but possible
B14: 5000000 | C14: =B14/C6 -> 4166.6667 | D14: =(B14/C6)/C7 -> 0.1112862 | E14: Very hard vs incumbents
B15: 10000000 | C15: =B15/C6 -> 8333.3333 | D15: =(B15/C6)/C7 -> 0.2225724 | E15: Implausible solo/IE-based
B16: Pro: recurring, higher retention, predictable. Con: to reach venture-scale ARR you must win double-digit % of a market owned by better-funded incumbents — the slow, expensive way.

Sheet Side-by-Side
B2: Side-by-side + the combined play
C4: Model 1 — Adviser SaaS | D4: Model 2 — Consumer lead-gen
B5: What you sell | C5: Time saved on fact-find/suitability admin | D5: Consented, pre-qualified adviser introductions
B6: Who pays | C6: Adviser firms (subscription) | D6: Advisers pay per lead; consumers free; minor ads
B7: TAM shape | C7: Seats × price (bounded) | D7: Consumers × lead value (large, portable)
B8: Defensibility | C8: Low — incumbents + CRM integration moat | D8: Medium-high — data, brand, two-sided network
B9: Your edge used? | C9: Weakly (generic admin) | D9: Strongly (education, visuals, Irish trust)
B10: Regulatory load | C10: Copilot OK, but suitability liability nearby | D10: Lighter — guidance/education; consent is key
B11: Main risk | C11: Losing to funded incumbents; slow B2B sales | D11: Consumer CAC / marketplace cold-start
B12: Venture precedent | C12: Aveni (raised, but you're behind) | D12: SmartAsset (unicorn), NerdWallet, Credit Karma
B13: Revenue quality | C13: Recurring, sticky | D13: Transactional, but scales + affiliate upside
B14: Verdict for scale | C14: Downstream upsell, not the spearhead | D14: Lead here
B16: The combined venture narrative (recommended)
B17: Own the consumer relationship and the data with Model 2, then monetise the advisers in your network three ways: (1) per-lead referrals, (2) affiliate/commission on products they place, (3) later, Model 1 tools sold to those same advisers. Each layer raises revenue per adviser and deepens the moat. That is the NerdWallet/Credit Karma playbook, localised to Irish advice and timed to auto-enrolment.
B21: Benchmarks used
B22: • | C22: SmartAsset: pay-per-lead $25–680 (by investable assets); now ~$25k/yr for 240–312 leads (~$80–100/lead); 89,000+ referrals delivered; avg ~$986k AUM/lead.
B23: • | C23: UK: Unbiased ~£65+VAT avg/lead (£87/mo + £43+/lead); shared leads £30–150; VouchedFor £60/mo directory.
B24: • | C24: Venture outcomes: SmartAsset ~$1bn+ valuation; NerdWallet IPO; Credit Karma acquired by Intuit for $7.1bn — all consumer-finance funnels monetised via provider referrals.

Sheet Engine 1 — White-Label
B2: Engine 1 — white-label API for advisers (early revenue)
B3: Advisers embed your branded AI planning chat + Irish-tax visuals on their own site. It converts their traffic into qualified, pre-filled leads. Recurring B2B cash with no consumer CAC — live in months. Benchmarked to Planswell ($450+/mo, one adviser per lead, completed plan included).
B5: Inputs
B6: Subscription per firm / month (€) | C6: 300 | E6: Planswell ~$450; adviser software £75–200. Mid = defensible
B7: One-off setup / onboarding fee (€) | C7: 500 | E7: Optional; aids cashflow + commitment
B8: Leads generated per firm / year (value proof) | C8: 40 | E8: Justifies price: 40 leads worth £65+ each >> €3,600/yr sub
B10: Revenue by phase
C11: Year 1 (design partners) | D11: Year 2 (Irish scale) | E11: Year 3 (UK entry)
B12: Paying firms | C12: 10 | D12: 60 | E12: 200
B13: MRR (subscriptions) | C13: =C12*C6 -> 3000 | D13: =D12*C6 -> 18000 | E13: =E12*C6 -> 60000
B14: Annual recurring revenue | C14: =C12*C6*12 -> 36000 | D14: =D12*C6*12 -> 216000 | E14: =E12*C6*12 -> 720000
B15: + setup fees (new firms, indic.) | C15: =C12*C7 -> 5000 | D15: =(D12-C12)*C7 -> 25000 | E15: =(E12-D12)*C7 -> 70000
B16: Why it's the easy first revenue: contracted, recurring, sold to an audience you already know (Brokers Ireland), no consumer CAC, and it seeds your future lead-buyers + training data.

Sheet Blended Plan
B2: Blended plan — two engines, mix shifts to consumer
B3: Engine 1 (white-label) is the reliable, no-CAC cash floor that funds the build. Engine 2 (consumer funnel) is CAC-contingent but is where scale and enterprise value come from. Rates pull from the 'Model 2 — Lead-Gen' sheet.
C5: Year 1 | D5: Year 2 | E5: Year 3
B6: Engine 1: paying firms | C6: 10 | D6: 60 | E6: 200
B7: Engine 1 revenue (white-label) | C7: =C6*'Engine 1 — White-Label'!C6*12 -> 36000 | D7: =D6*'Engine 1 — White-Label'!C6*12 -> 216000 | E7: =E6*'Engine 1 — White-Label'!C6*12 -> 720000
B8: Engine 2: consumer visitors / yr | C8: 50000 | D8: 300000 | E8: 1500000
B9: consented leads | C9: =C8*'Model 2 — Lead-Gen'!C6*'Model 2 — Lead-Gen'!C7 -> 1500 | D9: =D8*'Model 2 — Lead-Gen'!C6*'Model 2 — Lead-Gen'!C7 -> 9000 | E9: =E8*'Model 2 — Lead-Gen'!C6*'Model 2 — Lead-Gen'!C7 -> 45000
B10: lead / referral revenue | C10: =C9*'Model 2 — Lead-Gen'!C8 -> 120000 | D10: =D9*'Model 2 — Lead-Gen'!C8 -> 720000 | E10: =E9*'Model 2 — Lead-Gen'!C8 -> 3600000
B11: ad + affiliate revenue | C11: =C8*'Model 2 — Lead-Gen'!C9 -> 25000 | D11: =D8*'Model 2 — Lead-Gen'!C9 -> 150000 | E11: =E8*'Model 2 — Lead-Gen'!C9 -> 750000
B12: Engine 2 revenue (consumer) | C12: =C10+C11 -> 145000 | D12: =D10+D11 -> 870000 | E12: =E10+E11 -> 4350000
B13: TOTAL REVENUE | C13: =C7+C12 -> 181000 | D13: =D7+D12 -> 1086000 | E13: =E7+E12 -> 5070000
B14: Engine 1 share (de-risked B2B) | C14: =C7/C13 -> 0.19889503 | D14: =D7/D13 -> 0.19889503 | E14: =E7/E13 -> 0.14201183
B16: What each phase must prove (for the next raise)
B17: Year 1 | C17: White-label live with 10 design-partner firms + renewals; consumer content engine ranking on auto-enrolment terms; blended CAC < lead value. Fund via Enterprise Ireland HPSU + angels.
B18: Year 2 | C18: Repeatable, cheap consumer acquisition (organic majority) + first employer/provider distribution deal; marketplace lead-quality proof (lead→appointment→client). Raise seed.
B19: Year 3 | C19: UK entry for both engines; marketplace liquidity + net revenue retention on white-label; consumer scale to 1M+ visitors. Raise Series A on consumer growth + data moat.
