Workbook

Sheet Read Me
B2: Planéir Economics — Revised Model (v2)
B3: A more sceptical rebuild of the original fact-find model, plus a conversion-revenue reframe, pricing tiers, a competition benchmark, three business-model paths, and the Irish market backdrop. Prepared for Gerry, July 2026.
B5: How to read this workbook
B6: Blue text | C6: Editable input / scenario lever — change these
B7: Black text | C7: Formula — calculated, don't overtype
B8: Green text | C8: Links to another sheet
B9: Yellow fill | C9: Key lever that most moves the answer
B11: The sheets
B12: Adviser SaaS | C12: The original 'sell fact-find seats to advisers' case, rebuilt honestly: hard-cost ROI, value-capture %, and stress grid.
B13: Conversion & Pricing | C13: The reframe — models revenue from a small conversion lift, and shows ROI at €50 / €100 / €150 / €200 seat prices.
B14: Business Model Paths | C14: Side-by-side economics of three ways to commercialise: B2C advice funnel, B2B2C client tool, B2B admin SaaS.
B15: Competition | C15: Who already does 'cut adviser admin', what they charge, what they claim, and where Planéir actually differs.
B16: Market & Tailwinds | C16: The Irish backdrop: auto-enrolment wave, the advice gap, the Irish-tax localisation wedge. All sourced.
B18: The one-line verdict
B19: The admin-efficiency case breaks even at best and fights funded UK incumbents. The real, defensible value is Irish-specific, visual, education-led client acquisition — monetised through advice, riding the auto-enrolment wave. Price on that, not on saved minutes.
B23: Not investment advice. An analytical review of your own model and market. Figures are scenario assumptions to be replaced with pilot data.

Sheet Adviser SaaS
B2: Adviser SaaS case — rebuilt honestly
B3: Same cost engine as the original model, but reporting the numbers a buyer actually feels. Blue = input, yellow = key lever.
B5: Cost & workflow inputs | C5: Value
B6: Adviser salary (€ p.a.) | C6: 75000 | E6: Morgan McKinley private-banking midpoint
B7: Support / paraplanner salary (€ p.a.) | C7: 47500 | E7: IrishJobs paraplanner benchmark
B8: Employer PRSI | C8: 0.1115 | E8: Revenue.ie
B9: Benefits / pension load | C9: 0.05 | E9: Model assumption
B10: Weekly contracted hours | C10: 39 | E10: Model assumption
B11: Working weeks per year | C11: 46 | E11: Allows leave/training
B12: Adviser productive utilisation | C12: 0.7 | E12: Kitces productivity study
B13: Support productive utilisation | C13: 0.8 | E13: Model assumption
B14: Adviser hours per fact-find cycle | C14: 2 | E14: Allocated share of 3.75h workflow
B15: Support hours per fact-find cycle | C15: 1.75 | E15: Allocated share of 3.75h workflow
B16: Adviser charge-out rate (€/hr) | C16: 250 | E16: Oakwood Financial fee schedule
B17: Support charge-out rate (€/hr) | C17: 150 | E17: Oakwood Financial fee schedule
... B20: Monthly price per adviser (€) | C20: 200 | E20: KEY LEVER. See Conversion & Pricing for tiers
B22: Calculated outputs
B23: Loaded gross adviser hourly cost | C23: =C6*(1+C8+C9)/(C10*C11) -> 48.557692
B24: Loaded gross support hourly cost | C24: =C7*(1+C8+C9)/(C10*C11) -> 30.753205
B25: Net productive adviser hourly cost | C25: =C23/C12 -> 69.368132
B26: Net productive support hourly cost | C26: =C24/C13 -> 38.441506
B27: Internal economic cost per cycle | C27: =C14*C25+C15*C26 -> 206.0089 | E27: What an hour of freed time actually costs you
B28: Commercial capacity value per cycle | C28: =C14*C16+C15*C17 -> 762.5 | E28: Only real if freed time is re-sold at charge-out
B29: Annual subscription per adviser | C29: =C20*12 -> 2400
B30: Annual internal (hard-cost) saving | C30: =C27*C19*C18 -> 2472.1068 | E30: The money you can actually bank
B31: Annual capacity released (soft) | C31: =C28*C19*C18 -> 9150 | E31: Ceiling, not base case
B32: Hard-cost ROI | C32: =C30/C29 -> 1.0300445 | E32: Below 1.0x = customer loses money on hard cost
B33: Capacity-value ROI (optimistic) | C33: =C31/C29 -> 3.8125
B34: Share of hard saving captured by price | C34: =C29/C30 -> 0.97083184 | E34: Software usually captures 10–30%. Near 100% = mispriced
B36: Read: at €200 the tool captures almost all of the hard money it saves, leaving the buyer no cushion — so the sale must rest on the softer capacity and (unproven) conversion story. See next sheet.
B39: Hard-cost ROI stress grid (rows = time reduction, cols = cycles/yr)
B40: Time reduction ↓ / Cycles → | C40: 18 | D40: 24 | E40: 36
B41: 0.25 | C41: =(C27*0.25*18)/C29 -> 0.38626669 | D41: =(C27*0.25*24)/C29 -> 0.51502225 | E41: =(C27*0.25*36)/C29 -> 0.77253337
B42: 0.5 | C42: =(C27*0.5*18)/C29 -> 0.77253337 | D42: =(C27*0.5*24)/C29 -> 1.0300445 | E42: =(C27*0.5*36)/C29 -> 1.5450667
B43: 0.75 | C43: =(C27*0.75*18)/C29 -> 1.1588001 | D43: =(C27*0.75*24)/C29 -> 1.5450667 | E43: =(C27*0.75*36)/C29 -> 2.3176001
B44: Green ≥ 1.0x (customer at least breaks even on hard cost). Base case (50% × 24) sits on the knife-edge.

Sheet Conversion & Pricing
B2: The reframe — revenue, not saved minutes
B3: The model's best argument is buried: a converted advice client is worth far more than the admin a fact-find costs, so even a small conversion lift outweighs the whole time-saving. This is also the least-proven number — treat as a pilot hypothesis.
B5: Conversion inputs
B6: Fact-find cycles per adviser / year | C6: 24
B7: Baseline lead→client conversion | C7: 0.3
B8: Conversion lift from Planéir (percentage points) | C8: 0.03
B9: First-year value per advice client (€) | C9: 2000
B11: Outputs
B12: Extra clients per adviser / year | C12: =C6*C8 -> 0.72 | E12: cycles × conversion-point lift
B13: Annual conversion revenue per adviser | C13: =C12*C9 -> 1440 | E13: The prize the original model ignored
C14: ='Adviser SaaS'!C30 -> 2472.1068
B15: Conversion revenue ÷ hard-cost saving | C15: =C13/C14 -> 0.58249911 | E15: Above 1.0x = conversion is the bigger lever
B17: Even a 3-point conversion lift can rival or beat the entire admin saving — and dwarf it if client value is higher. That is the pitch that survives contact with Aveni; 'we save minutes' is not.
B20: What ROI looks like at different seat prices
B21: Monthly seat price | C21: Annual subscription | D21: Hard-cost ROI | E21: Cost + conversion ROI | F21: Capacity + conversion ROI
B22: 50 | C22: =B22*12 -> 600 | D22: =C14/(B22*12) -> 4.120178 | E22: =(C14+C13)/(B22*12) -> 6.520178 | F22: =('Adviser SaaS'!C31+C13)/(B22*12) -> 17.65
B23: 100 | C23: =B23*12 -> 1200 | D23: =C14/(B23*12) -> 2.060089 | E23: =(C14+C13)/(B23*12) -> 3.260089 | F23: =('Adviser SaaS'!C31+C13)/(B23*12) -> 8.825
B24: 150 | C24: =B24*12 -> 1800 | D24: =C14/(B24*12) -> 1.3733927 | E24: =(C14+C13)/(B24*12) -> 2.1733927 | F24: =('Adviser SaaS'!C31+C13)/(B24*12) -> 5.8833333
B25: 200 | C25: =B25*12 -> 2400 | D25: =C14/(B25*12) -> 1.0300445 | E25: =(C14+C13)/(B25*12) -> 1.6300445 | F25: =('Adviser SaaS'!C31+C13)/(B25*12) -> 4.4125
B26: 300 | C26: =B26*12 -> 3600 | D26: =C14/(B26*12) -> 0.68669633 | E26: =(C14+C13)/(B26*12) -> 1.0866963 | F26: =('Adviser SaaS'!C31+C13)/(B26*12) -> 2.9416667
B27: At €200 the hard-cost case is ~break-even; dropping to €100–150 gives the buyer a real cushion while conversion revenue carries the upside. Amber row = a defensible list price to test.

Sheet Business Model Paths
B2: Three ways to commercialise — rough economics
B3: Same expertise and tooling, three routes to market. Numbers are illustrative scenario inputs (blue), not forecasts — they exist to compare shape, scale and defensibility.
C5: Path A — B2C advice funnel | D5: Path B — B2B2C client tool | E5: Path C — B2B admin SaaS
B6: What it is | C6: Your own visual education calls → regulated advice clients. The live Planéir, monetised. | D6: License the Irish-tax visual planning tool to other brokers as a client-facing add-on. | E6: Sell fact-find/admin-efficiency seats to adviser firms (the original model).
B7: Who pays | C7: The consumer (indirectly, via advice fees / commission) | D7: Adviser firms (per seat, client-facing add-on) | E7: Adviser firms (per seat, back-office)
B8: Core value proposition | C8: Understand your money before you decide. Trust + clarity. | D8: Win & retain more clients with Irish-accurate visuals UK tools can't do. | E8: Cut fact-find & suitability admin time.
B9: Illustrative drivers (blue = edit)
B10: Volume × time | C10: 6 | D10: 1250 | E10: 1061
B11: × rate | C11: 46 | D11: 0.08 | E11: 0.6
B12: × conversion | C12: 0.2 | D12: 2 | E12: 0.05
B13: × unit value | C13: 2000 | D13: 75 | E13: 2400
B14: (rows above, per path: volume · reach · conversion · unit price — labels differ by path)
B16: Indicative annual revenue | C16: =C10*C11*C12*C13 -> 110400 | D16: =D10*D11*D12*D13*12 -> 180000 | E16: =E10*E11*E12*E13 -> 76392
B17: Scales beyond your hours? | C17: No — capped by your diary; grows only by hiring advisers | D17: Yes — SaaS margins once built | E17: Yes — but tiny home market
B18: Defensible vs incumbents? | C18: Yes — trust + Irish visual niche (askpaul proves demand) | D18: Yes — Irish tax + client-facing; UK tools can't localise | E18: No — Aveni/AdvisoryAI outgun on the same job
B19: Biggest risk | C19: Time-capped income; regulated advice workload | D19: Slow B2B broker sales; small market | E19: Break-even ROI; funded competition; needs UK scale
B20: Verdict | C20: Fastest cash, proven, but a practice not a scale-up | D20: Best fit for your edge — defensible & scalable | E20: Weakest — don't lead with this

Sheet Competition
B2: Competition — who already owns 'cut adviser admin'
B3: The original model had no competition line. This is it. The back-office admin job is crowded and funded; Planéir's whitespace is the client-facing, Irish-tax, education layer.
B5: Tool | C5: Primary job | D5: Claimed saving / edge | E5: Integrations | F5: Indic. price | G5: Geo | H5: Overlap with Planéir
B6: Aveni Assist | C6: Suitability reports, letters, reviews from templates | D6: 'Cut admin ~90%'; 90→10 min/report | E6: Intelliflo Office, Xplan | F6: Bespoke / enterprise | G6: UK | H6: HIGH — same admin job, better funded & integrated
B7: AdvisoryAI (Emma & Evie) | C7: Suitability writing + meeting notes + fact-find updates | D7: Report drafting in your templates | E7: CRM + meeting platforms | F7: Published per-seat plans | G7: UK | H7: HIGH — direct on admin
B8: Saturn | C8: Meeting assistant, fact-check vs suitability | D8: Real-time meeting support | E8: Meeting platforms | F8: Bespoke | G8: UK | H8: MEDIUM — meeting layer
B9: FE CashCalc | C9: Cashflow modelling | D9: Planning visuals | E9: Various | F9: ~£75 / mo | G9: UK/IE | H9: MEDIUM — visuals, but UK tax
B10: Plannr | C10: CRM + workflow | D10: All-in-one practice mgmt | E10: Native | F10: ~£140 / mo | G10: UK | H10: LOW — different layer (CRM)
B11: Intelliflo Office | C11: Incumbent adviser CRM | D11: Market-leading back office | E11: Ecosystem | F11: Bespoke, contracted | G11: UK/IE | H11: LOW — infrastructure, not advice UX
B12: Planéir (proposed) | C12: Client-facing visual education + Irish-tax planning | D12: Understanding & conversion, Irish-accurate | E12: Own app | F12: €100–200 / mo (test) | G12: Ireland | H12: — this is the whitespace
B14: Takeaways
B15: 1. On 'save admin time', Planéir is entering late, priced high, and claiming less (50%) than incumbents advertise (~90%). Don't fight here.
B16: 2. The incumbents are UK-built and UK-tax. None model Irish SFT/ARF/lump-sum rules — a genuine, defensible localisation wedge.
B17: 3. None lead with a client-facing visual education experience. That, plus a QFA's trust, is Planéir's actual differentiation.
B18: 4. Implication: compete on client understanding & conversion for the Irish market, not on back-office minutes.

Sheet Market & Tailwinds
B2: Market & tailwinds — the Irish backdrop
B3: Why the timing favours a consumer education play right now. All figures sourced; these are the demand-side facts the economics model should sit on.
B5: Theme | C5: Figure | D5: Detail | E5: Source
B6: Auto-enrolment launched | C6: Jan 2026 | D6: 'My Future Fund' — mandatory auto-enrolment now live; a one-off wave of first-time pension savers needing education | E6: gov.ie / CSO
B7: Newly enrolled workers | C7: ~763,000 | D7: Employees auto-enrolled across ~104,000 employers; ~800k get a workplace pension for the first time | E7: gov.ie (My Future Fund)
B8: Who's eligible | C8: 23–60, >€20k | D8: Not already in a scheme — precisely the disengaged, under-advised segment | E8: L&E Global / NFP
B9: Advice gap | C9: 66% | D9: Two-thirds of adults have NEVER spoken 1:1 to an adviser about retirement | E9: Bluewater FP / industry
B10: Preparedness gap | C10: 21% | D10: 74% feel they manage day-to-day money well, but only 21% feel prepared for retirement (10% of 55–64s) | E10: Bluewater FP
B11: Access divide | C11: 12% vs 51% | D11: Only 12% of lower socio-economic (DE) have seen an adviser vs 51% of AB — a big underserved middle | E11: Bluewater FP
B12: Pension coverage | C12: ~two-thirds | D12: Q3 2025: ~66% of workers have some supplementary cover; lowest among the young | E12: CSO Pension Coverage 2025
B13: Adviser seats (narrow) | C13: 1,061 | D13: FPSB Ireland certified holistic planners — the model's TAM base | E13: FPSB Ireland
B14: Broker firms | C14: 1,200–1,250 | D14: Brokers Ireland member firms (insurance/financial/mortgage) | E14: Brokers Ireland
B15: QFA holders (broad) | C15: 22,000+ | D15: Total QFA designations — a ceiling, not practising holistic advisers | E15: IOB
B16: Localisation wedge | C16: SFT / ARF | D16: Irish pension tax (Standard Fund Threshold, ARF, lump-sum) is 'one of the most technically complex areas' — UK tools don't model it | E16: Chase Buchanan / opesfp
B17: B2C competitors | C17: askpaul, Money Smart, Elevate | D17: Content-led Irish advice already works (askpaul) — validation AND competition; incumbents Irish Life, Standard Life | E17: bestinireland / vendor sites
B19: So what
B20: ~800,000 newly-enrolled, mostly-disengaged savers who don't understand pensions, arriving in the same 12 months, in a market where UK tools can't speak Irish tax and a QFA with a visual explainer can. That is the opening — and it is a consumer-education/advice opening, not a back-office-SaaS one.
